Verilog/4X1_mux.v
module mux_4x1(
	input [7:0]I0,
	input [7:0]I1,
	input [7:0]I2,
	input [7:0]I3,
	input [1:0]sel,
	output reg [7:0]out
	);
	
	always @(*)
		begin
			case (sel)
				2'b00 : out = I0;
				2'b01 : out = I1;
				2'b10 : out = I2;
				2'b11 : out = I3;
			endcase	
			
		end
		
endmodule

Verilog/8-bitALU.v

// #####################################################              ALU begins            ##############################################################

module bit_8_AND(aANDb,A,B);
	output reg [7:0] aANDb;
	input [7:0]A,B;
	always @(*)
		begin
			aANDb <= A&B;
		end
endmodule

module bit_8_OR(
	output reg [7:0]aORb,
	input [7:0]A,
	input [7:0]B
);
	always @(*)
		begin
			aORb <= A|B;
		end
endmodule

module bit_8_ADDER(
	output reg [7:0]aPlusb,
	input [7:0]A,
	input [7:0]B,
	input carry_in
);
	reg BB;
	always @(*)
		begin
			if(carry_in == 1)
				BB = ~B;
			else
				BB = B;
			aPlusb = A + BB;
		end
endmodule

module mux_2X1(
	output reg [7:0]O,
	input [7:0]I0,
	input [7:0]I1,
	input sel);

	always @(*)
		begin
			if(sel == 0)
				O <= I0;
			else
				O <= I1;
		end
endmodule


module bit_8_ALU(
	input [7:0]in_A,
	input [7:0]in_B,
	input [1:0]in_operation,
	output [7:0]out_c
);
	
	wire [7:0]out_and,out_or,out_adder,mux1;
	
	bit_8_AND i1(out_and,in_A,in_B);
	bit_8_OR i2(out_or,in_A,in_B);
	bit_8_ADDER i3(out_adder,in_A,in_B,in_operation[0]);
	
	mux_2X1 i4(mux1,out_and,out_or,in_operation[0]);
	mux_2X1 i5(out_c,mux1,out_adder,in_operation[1]);
	
endmodule

// #####################################################              ALU Ends               ##############################################################

Verilog/8-bit-resister.v
module register8(
	input clk,
	input [7:0]data_in,
	input enable,
	output reg [7:0]data_out
	);
	
	always @(posedge clk & enable)
		begin
				data_out <= data_in;
		end
		
endmodule

Verilog/controlUnit.v
/*
=================== ================================== ======================
                    8-Bit Von Neumann Architecture CPU
------------------  ~~~~~~~~~~~~~~~~~~~~~~~~~~~~~~~~~~  ---------------------
                Group 40 :  Praveen Kumar Gupta - 16CO235
                            Durvesh Bhalekar    - 16CO210
-----------------------------------------------------------------------------


=============================================================================
*/

// Define Timesacle for the verilog file.
`timescale 1ns/100ps

module cpu( clk,zero, negative, irload,imload, pcsel,pcload,readwrite,dwrite,
            irvalue,dbus,sbus,dval,pcin,imm,datain,aluout,address,
            dregsel, sregsel, aluop, regsel, addrsel);

    input wire clk,zero, negative, irload,imload, pcsel,pcload,readwrite,dwrite;
    input wire [1:0] dregsel, sregsel, aluop, regsel, addrsel;
    inout wire [7:0] irvalue,dbus,sbus,dval,pcin,imm,datain,aluout,address; 
    //input  address;
    ram RAM(aluout,address,readwrite,clk,datain);
    
    register8 InstrREG(clk,datain,irload,irvalue);
    register8 ImmREG(clk,datain,imload,imm);
    control CTRL(clk, zero, negative, irvalue, dregsel, sregsel, aluop, irload, 
    imload, pcsel, pcload, readwrite, regsel, dwrite, addrsel);
    bit_8_ALU ALU(dbus,sbus,aluop,aluout);  
    registerFile RF(dval,dwrite,dregsel,sregsel,dregsel,zero,negative,dbus,sbus);
    pcBlock PC(clk,pcin,pcload,imm,pcsel,sbus,dbus,addrsel,address);
    

endmodule
module pcBlock(clk,pcin,pcload,imm,pcsel,sbus,dbus,addrsel,address);

    input clk,pcload,pcsel;
    input [7:0] imm,sbus,dbus;
    inout [7:0] pcin;
    input [1:0] addrsel;
    output [7:0] address;
    wire [7:0] pcout;
    reg [7:0] pcadd;
    initial
        begin
            pcadd = 8'b00000000;
            //pcout = 8'b00000000;
        end
    register8 PCREG(clk,pcin,pcload,pcout);
    always @(pcout)
        pcadd <= pcout + 1'b1;
    mux_2X1 pcInMux(pcin,imm,pcadd,pcsel);
    mux_4x1 addressMux(pcout,imm,sbus,dbus,addrsel,address);

endmodule

// Module for the Control Unit which splits the instruction and
// sets the values for various flags which acts as enable or selector
// for the Multiplexers used in Main CPU module
module control(clk, zero, negative, irvalue, dregsel, sregsel, aluop, irload,
 imload, pcsel, pcload, readwrite, regsel, dwrite, addrsel);

    // 8-Bit value from Instruction Register
    input [7:0] irvalue;
    // Clock & Zero, Negative flag from ALU
    input clk, zero, negative;

    // First 4 Bits of IR
    reg irbit4, irbit5, irbit6, irbit7;
    // OPcodes and destination reg, source reg value (Refer dataflow)
    reg [1:0] op1,op2,rd,rs;

    //Phase : 0-Fetch 1-Decode 2-Execute
    wire [1:0] phase;
    // 4Bits Opcode = concat(op1,op2)
    reg [3:0] op1op2;

    output reg [1:0] dregsel, sregsel, aluop;
    output [1:0] regsel,addrsel;
    output irload, imload, pcsel, pcload, readwrite,  dwrite ;

    always @(irvalue)
        begin
            irbit7 <= irvalue[7];
            irbit6 <= irvalue[6];
            irbit5 <= irvalue[5];
            irbit4 <= irvalue[4];

            op1 <= {irvalue[7],irvalue[6]};
            op2 <= {irvalue[5],irvalue[4]};
            rd  <= {irvalue[3],irvalue[2]};
            rs  <= {irvalue[1],irvalue[0]};
            op1op2 <= {irvalue[7],irvalue[6],irvalue[5],irvalue[4]};
        end

    always @(rd or rs or op2)
    begin
        dregsel <= rd;
        sregsel <= rs;
        aluop <= op2;
    end

    phaseCounter PHASE(clk, phase);
    irLoad IR(phase,irload);
    imLoad IM(phase,irbit7,imload);
    pcSelect PC(phase, pcsel);
    pcLoad PCLOAD(zero, negative, irbit4, irbit5, irbit6, irbit7, op2, phase, pcload);
    readWrite RW(irbit4 , irbit5, irbit6, phase, readwrite);
    regSel REGSEL(op1op2,phase,regsel);
    destRegWrite DR(op1op2,phase,dwrite);
    addressSelect AS(op1op2,phase,addrsel);

endmodule

module phaseCounter(input clk,output reg [1:0] phase);
    initial 
        phase = 2'b00;
    always @(posedge clk)
        begin
            if(phase==2'b10)
                phase <= 2'b00;
            else
                phase <= phase+1;
        end
endmodule

module irLoad(input [1:0] phase,output reg irload);
    always @(phase)
    begin
        if(phase == 2'b00)
            irload <=1;
        else
            irload <=0;
    end 
endmodule

module imLoad(input [1:0] phase,input irbit7,output reg imload);
    always @(phase)
    begin
        if(phase == 2'b01)
            imload <= irbit7;
        else
            imload <= 0;
    end 
endmodule

module pcSelect(input [1:0] phase,output reg pcsel);
    always @(phase)
    begin
        if(phase[1] == 0)
            pcsel <= 1;
        else
            pcsel <= 0;
    end 
endmodule

module pcLoad(zero, negative, irbit4, irbit5, irbit6, irbit7, op2, phase, pcload);
    input zero,negative,irbit4, irbit5, irbit6, irbit7;
    input [1:0] op2,phase;
    output reg pcload;
    reg mux1out;
    always @(op2)
    begin
        case(op2)
            2'b00 : mux1out <= zero;
            2'b01 : mux1out <= ~zero;
            2'b10 : mux1out <= (~zero)&(~negative);
            2'b11 : mux1out <= negative;
        endcase
    end
    always @(phase or mux1out)
    begin
        case(phase)
            2'b00 : pcload <= 1;
            2'b01 : pcload <= irbit7;
            2'b10 : pcload <= (mux1out & irbit7 & ~irbit6) | (irbit4 & irbit5 & irbit6 & irbit7);
            2'b11 : pcload <= 0;
        endcase
    end
endmodule

module readWrite(irbit4 , irbit5, irbit6, phase, readwrite);
    input irbit4,irbit5,irbit6,irbit7;
    input [1:0] phase;
    output reg readwrite;
    always @(phase)
    begin
        case(phase)
            2'b00 : readwrite <= 0;
            2'b01 : readwrite <= 0;
            2'b10 : readwrite <= irbit4 & ~irbit5 & irbit6;
            2'b11 : readwrite <= 0;
        endcase
    end

endmodule

module regSel(op1op2,phase,regsel);
    input [3:0] op1op2;
    input [1:0] phase;
    output reg [1:0] regsel;
    reg [1:0] mux1out;
    always @(op1op2)
        begin
            case(op1op2)
                 4'b0000,4'b0001,4'b0010,4'b0011   : mux1out <= 2'b11;
                 4'b0100,4'b110  :                   mux1out <= 2'b10;
                 4'b0110:                            mux1out <= 2'b01;
                 default :                           mux1out <= 2'b00;              
            endcase  
        end
    always @(phase or mux1out)
    begin
        case(phase)
            2'b10 : regsel <= mux1out;
            default : regsel <= 0;
        endcase
    end    
endmodule

module destRegWrite(op1op2,phase,dwrite);
    input [3:0] op1op2;
    input [1:0] phase;
    output reg dwrite;
    reg [1:0] mux1out;
    always @(op1op2)
        begin
            case(op1op2)
                 4'b0000,4'b0001,4'b0010,4'b0011,4'b0100,4'b0110,4'b1100,4'b1110 : mux1out <= 2'b11;
                 default :                           mux1out <= 2'b00;              
            endcase  
        end
    always @(phase or mux1out)
    begin
        case(phase)
            2'b10 : dwrite <= mux1out;
            default : dwrite <= 0;
        endcase
    end 
endmodule


module addressSelect(op1op2,phase,addrsel);
    input [3:0] op1op2;
    input [1:0] phase;
    output reg [1:0] addrsel;
    reg [1:0] mux1out;
    always @(op1op2)
        begin
            case(op1op2)
                 4'b1110,4'b1101 : mux1out <= 2'b01;
                 4'b0100,4'b0101 : mux1out <= 2'b10;
                 default :         mux1out <= 2'b00;              
            endcase  
        end
    always @(phase or mux1out)
    begin
        case(phase)
            2'b10 : addrsel <= mux1out;
            default : addrsel <= 0;
        endcase
    end 
endmodule

Verilog/registerFile.v
/*module register8(
	input clk,
	input [7:0]data_in,
	input enable,
	output reg [7:0]data_out
	);
	
	always @(posedge clk & enable)
		begin
				data_out <= data_in;
		end
		
endmodule
*/
module mux(I0,I1,I2,I3,sel,out);
	input [7:0]I0,I1,I2,I3;
	input [1:0] sel;
	output reg [7:0] out;
	always @(*)
		begin
			case (sel)
				2'b00 : out = I0;
				2'b01 : out = I1;
				2'b10 : out = I2;
				2'b11 : out = I3;
			endcase	
			
		end
		
endmodule


module demux(
	input I0,
	input [1:0]sel,
	output reg o0,
	output reg o1,
	output reg o2,
	output reg o3
	);
	
	always @(*)
		begin
			case (sel)
				2'b00 : 
						begin 
							o0 = I0;
							o1 = 1'b0;
							o2 = 1'b0;
							o3 = 1'b0;
						end
				2'b01 : 
						begin 
							o0 = 1'b0;
							o1 = I0;
							o2 = 1'b0;
							o3 = 1'b0;
						end
				2'b10 : 
						begin 
							o0 = 1'b0;
							o1 = 1'b0;
							o2 = I0;
							o3 = 1'b0;
						end
				2'b11 : 
						begin 
							o0 = 1'b0;
							o1 = 1'b0;
							o2 = 1'b0;
							o3 = I0;
						end
			endcase				
		end		
endmodule

module registerFile(
	input [7:0]dval,
	input dwrite,
	input [1:0]dresel,
	input [1:0]sregel,
	input [1:0] drs,
	output reg zero,
	output reg negative,
	output [7:0]dbus,
	output [7:0]sbus
	);
	
	wire [3:0]res_enable;
	wire [7:0]res0,res1,res2,res3;
	demux demux1(dwrite, drs, res_enable[0],res_enable[1],res_enable[2],res_enable[3]);
	register8 r0(clk , dval, res_enable[0], res0 );
	register8 r1(clk , dval, res_enable[1], res1 );
	register8 r2(clk , dval, res_enable[2], res2 );
	register8 r3(clk , dval, res_enable[3], res3 );
	
	mux mux1(res0, res1, res2, res3, dresel , dbus);
	mux mux2(res0, res1, res2, res3, sregel , sbus);

	always @(posedge clk)
		begin
			negative <= dbus[7];
			zero <= dbus[0]|dbus[1]|dbus[2]|dbus[3]|dbus[4]|dbus[5]|dbus[6]|dbus[7];			
		end
endmodule

Verilog/single_port_ram.v
module ram (data,addr,we, clk,q);
	input [7:0] data, addr;
	input we, clk;	
	output reg [7:0] q;

	// Declare the RAM variable
	reg [7:0] ram[255:0];
	
	// Variable to hold the registered read address
	reg [7:0] addr_reg;

	initial
		begin
			ram[0]=8'b11000000;
            ram[1]=8'b00000100;
            ram[2]=8'b11000100;
            ram[3]=8'b00000010;
            ram[4]=8'b00100100;
            ram[5]=8'b00000000;
		end 
	initial
		q <= ram[0];
	always @ (posedge clk)
	begin
	// Write
		if (we)
			ram[addr] <= data;
		
		q <= ram[addr];		
	end	
endmodule

Verilog/test.v
`timescale 1ns/100ps

module test;
    reg clk,zero, negative, irload,imload, pcsel,pcload,readwrite,dwrite;

    //wire [7:0] irvalue;
    wire [7:0] irvalue,dbus,sbus,dval,pcin,imm,datain,aluout,address;
    reg [1:0] dregsel, sregsel, aluop, regsel, addrsel;

    cpu CPU(clk,zero, negative, irload,imload, pcsel,pcload,readwrite,dwrite,
            irvalue,dbus,sbus,dval,pcin,imm,datain,aluout,address,
            dregsel, sregsel, aluop,regsel, addrsel);


    initial
        begin
            $dumpfile("wave.vcd");
            $dumpvars(0,test);
            $display("8-Bit Von Neumann CPU");
            //$display("");

            clk <= 1'b0;
            zero <= 1'b0;
            negative <= 1'b0;
            irload <= 1'b0;
            imload <= 1'b0;
            pcsel <= 1'b0;
            pcload <= 1'b0;
            readwrite <= 1'b0;
            dwrite <= 1'b0;
            
            /*
            //irvalue <= 8'b00000000;
            dbus <= 8'b00000000;
            sbus <= 8'b00000000;
            dval <= 8'b00000000;
            pcin <= 8'b00000000;
            imm <= 8'b00000000;
            datain <= 8'b00000000;
            aluout <= 8'b00000000;
            address <= 8'b00000000;
            imm <= 8'b00000000;*/

            dregsel <= 2'b00;
            sregsel <= 2'b00;
            aluop <= 2'b00;
            regsel <= 2'b00;
            addrsel <= 2'b00;

        end
    initial
        forever
        #5 clk = ~clk;

    initial
        begin//fork
            #100;          
            $finish;
        end//join
    initial
            $monitor("Phasekk = %b",);
            //$monitor("%gns\t%b\t%b\t%b\t%b\t%b\t%b\t%b\t%b\t%b",$time,ir,irbit7,irbit6,irbit5,irbit4,op1,op2,rs,rd,op1op2);

endmodule

Verilog/wave.vcd
$date
	Sun Nov  5 15:04:23 2017
$end
$version
	Icarus Verilog
$end
$timescale
	100ps
$end
$scope module test $end
$var wire 8 ! address [7:0] $end
$var wire 8 " aluout [7:0] $end
$var wire 8 # datain [7:0] $end
$var wire 8 $ dbus [7:0] $end
$var wire 8 % dval [7:0] $end
$var wire 8 & imm [7:0] $end
$var wire 8 ' irvalue [7:0] $end
$var wire 8 ( pcin [7:0] $end
$var wire 8 ) sbus [7:0] $end
$var reg 2 * addrsel [1:0] $end
$var reg 2 + aluop [1:0] $end
$var reg 1 , clk $end
$var reg 2 - dregsel [1:0] $end
$var reg 1 . dwrite $end
$var reg 1 / imload $end
$var reg 1 0 irload $end
$var reg 1 1 negative $end
$var reg 1 2 pcload $end
$var reg 1 3 pcsel $end
$var reg 1 4 readwrite $end
$var reg 2 5 regsel [1:0] $end
$var reg 2 6 sregsel [1:0] $end
$var reg 1 7 zero $end
$scope module CPU $end
$var wire 8 8 address [7:0] $end
$var wire 2 9 addrsel [1:0] $end
$var wire 2 : aluop [1:0] $end
$var wire 8 ; aluout [7:0] $end
$var wire 1 < clk $end
$var wire 8 = datain [7:0] $end
$var wire 8 > dbus [7:0] $end
$var wire 2 ? dregsel [1:0] $end
$var wire 8 @ dval [7:0] $end
$var wire 1 A dwrite $end
$var wire 1 B imload $end
$var wire 8 C imm [7:0] $end
$var wire 1 D irload $end
$var wire 8 E irvalue [7:0] $end
$var wire 1 F negative $end
$var wire 8 G pcin [7:0] $end
$var wire 1 H pcload $end
$var wire 1 I pcsel $end
$var wire 1 J readwrite $end
$var wire 2 K regsel [1:0] $end
$var wire 8 L sbus [7:0] $end
$var wire 2 M sregsel [1:0] $end
$var wire 1 N zero $end
$scope module RAM $end
$var wire 8 O addr [7:0] $end
$var wire 1 < clk $end
$var wire 8 P data [7:0] $end
$var wire 1 J we $end
$var reg 8 Q q [7:0] $end
$upscope $end
$scope module InstrREG $end
$var wire 1 < clk $end
$var wire 8 R data_in [7:0] $end
$var wire 1 D enable $end
$var reg 8 S data_out [7:0] $end
$upscope $end
$scope module ImmREG $end
$var wire 1 < clk $end
$var wire 8 T data_in [7:0] $end
$var wire 1 B enable $end
$var reg 8 U data_out [7:0] $end
$upscope $end
$scope module CTRL $end
$var wire 2 V addrsel [1:0] $end
$var wire 1 < clk $end
$var wire 1 A dwrite $end
$var wire 1 B imload $end
$var wire 1 D irload $end
$var wire 8 W irvalue [7:0] $end
$var wire 1 F negative $end
$var wire 1 H pcload $end
$var wire 1 I pcsel $end
$var wire 2 X phase [1:0] $end
$var wire 1 J readwrite $end
$var wire 2 Y regsel [1:0] $end
$var wire 1 N zero $end
$var reg 2 Z aluop [1:0] $end
$var reg 2 [ dregsel [1:0] $end
$var reg 1 \ irbit4 $end
$var reg 1 ] irbit5 $end
$var reg 1 ^ irbit6 $end
$var reg 1 _ irbit7 $end
$var reg 2 ` op1 [1:0] $end
$var reg 4 a op1op2 [3:0] $end
$var reg 2 b op2 [1:0] $end
$var reg 2 c rd [1:0] $end
$var reg 2 d rs [1:0] $end
$var reg 2 e sregsel [1:0] $end
$scope module PHASE $end
$var wire 1 < clk $end
$var reg 2 f phase [1:0] $end
$upscope $end
$scope module IR $end
$var wire 2 g phase [1:0] $end
$var reg 1 h irload $end
$upscope $end
$scope module IM $end
$var wire 1 i irbit7 $end
$var wire 2 j phase [1:0] $end
$var reg 1 k imload $end
$upscope $end
$scope module PC $end
$var wire 2 l phase [1:0] $end
$var reg 1 m pcsel $end
$upscope $end
$scope module PCLOAD $end
$var wire 1 n irbit4 $end
$var wire 1 o irbit5 $end
$var wire 1 p irbit6 $end
$var wire 1 i irbit7 $end
$var wire 1 F negative $end
$var wire 2 q op2 [1:0] $end
$var wire 2 r phase [1:0] $end
$var wire 1 N zero $end
$var reg 1 s mux1out $end
$var reg 1 t pcload $end
$upscope $end
$scope module RW $end
$var wire 1 n irbit4 $end
$var wire 1 o irbit5 $end
$var wire 1 p irbit6 $end
$var wire 1 u irbit7 $end
$var wire 2 v phase [1:0] $end
$var reg 1 w readwrite $end
$upscope $end
$scope module REGSEL $end
$var wire 4 x op1op2 [3:0] $end
$var wire 2 y phase [1:0] $end
$var reg 2 z mux1out [1:0] $end
$var reg 2 { regsel [1:0] $end
$upscope $end
$scope module DR $end
$var wire 4 | op1op2 [3:0] $end
$var wire 2 } phase [1:0] $end
$var reg 1 ~ dwrite $end
$var reg 2 !" mux1out [1:0] $end
$upscope $end
$scope module AS $end
$var wire 4 "" op1op2 [3:0] $end
$var wire 2 #" phase [1:0] $end
$var reg 2 $" addrsel [1:0] $end
$var reg 2 %" mux1out [1:0] $end
$upscope $end
$upscope $end
$scope module ALU $end
$var wire 8 &" in_A [7:0] $end
$var wire 8 '" in_B [7:0] $end
$var wire 2 (" in_operation [1:0] $end
$var wire 8 )" mux1 [7:0] $end
$var wire 8 *" out_adder [7:0] $end
$var wire 8 +" out_and [7:0] $end
$var wire 8 ," out_c [7:0] $end
$var wire 8 -" out_or [7:0] $end
$scope module i1 $end
$var wire 8 ." A [7:0] $end
$var wire 8 /" B [7:0] $end
$var reg 8 0" aANDb [7:0] $end
$upscope $end
$scope module i2 $end
$var wire 8 1" A [7:0] $end
$var wire 8 2" B [7:0] $end
$var reg 8 3" aORb [7:0] $end
$upscope $end
$scope module i3 $end
$var wire 8 4" A [7:0] $end
$var wire 8 5" B [7:0] $end
$var wire 1 6" carry_in $end
$var reg 1 7" BB $end
$var reg 8 8" aPlusb [7:0] $end
$upscope $end
$scope module i4 $end
$var wire 8 9" I0 [7:0] $end
$var wire 8 :" I1 [7:0] $end
$var wire 1 ;" sel $end
$var reg 8 <" O [7:0] $end
$upscope $end
$scope module i5 $end
$var wire 8 =" I0 [7:0] $end
$var wire 8 >" I1 [7:0] $end
$var wire 1 ?" sel $end
$var reg 8 @" O [7:0] $end
$upscope $end
$upscope $end
$scope module RF $end
$var wire 1 A" clk $end
$var wire 8 B" dbus [7:0] $end
$var wire 2 C" dresel [1:0] $end
$var wire 2 D" drs [1:0] $end
$var wire 8 E" dval [7:0] $end
$var wire 1 A dwrite $end
$var wire 8 F" res0 [7:0] $end
$var wire 8 G" res1 [7:0] $end
$var wire 8 H" res2 [7:0] $end
$var wire 8 I" res3 [7:0] $end
$var wire 4 J" res_enable [3:0] $end
$var wire 8 K" sbus [7:0] $end
$var wire 2 L" sregel [1:0] $end
$var reg 1 M" negative $end
$var reg 1 N" zero $end
$scope module demux1 $end
$var wire 1 A I0 $end
$var wire 2 O" sel [1:0] $end
$var reg 1 P" o0 $end
$var reg 1 Q" o1 $end
$var reg 1 R" o2 $end
$var reg 1 S" o3 $end
$upscope $end
$scope module r0 $end
$var wire 1 A" clk $end
$var wire 8 T" data_in [7:0] $end
$var wire 1 U" enable $end
$var reg 8 V" data_out [7:0] $end
$upscope $end
$scope module r1 $end
$var wire 1 A" clk $end
$var wire 8 W" data_in [7:0] $end
$var wire 1 X" enable $end
$var reg 8 Y" data_out [7:0] $end
$upscope $end
$scope module r2 $end
$var wire 1 A" clk $end
$var wire 8 Z" data_in [7:0] $end
$var wire 1 [" enable $end
$var reg 8 \" data_out [7:0] $end
$upscope $end
$scope module r3 $end
$var wire 1 A" clk $end
$var wire 8 ]" data_in [7:0] $end
$var wire 1 ^" enable $end
$var reg 8 _" data_out [7:0] $end
$upscope $end
$scope module mux1 $end
$var wire 8 `" I0 [7:0] $end
$var wire 8 a" I1 [7:0] $end
$var wire 8 b" I2 [7:0] $end
$var wire 8 c" I3 [7:0] $end
$var wire 2 d" sel [1:0] $end
$var reg 8 e" out [7:0] $end
$upscope $end
$scope module mux2 $end
$var wire 8 f" I0 [7:0] $end
$var wire 8 g" I1 [7:0] $end
$var wire 8 h" I2 [7:0] $end
$var wire 8 i" I3 [7:0] $end
$var wire 2 j" sel [1:0] $end
$var reg 8 k" out [7:0] $end
$upscope $end
$upscope $end
$scope module PC $end
$var wire 8 l" address [7:0] $end
$var wire 2 m" addrsel [1:0] $end
$var wire 1 < clk $end
$var wire 8 n" dbus [7:0] $end
$var wire 8 o" imm [7:0] $end
$var wire 8 p" pcin [7:0] $end
$var wire 1 H pcload $end
$var wire 8 q" pcout [7:0] $end
$var wire 1 I pcsel $end
$var wire 8 r" sbus [7:0] $end
$var reg 8 s" pcadd [7:0] $end
$scope module PCREG $end
$var wire 1 < clk $end
$var wire 8 t" data_in [7:0] $end
$var wire 1 H enable $end
$var reg 8 u" data_out [7:0] $end
$upscope $end
$scope module pcInMux $end
$var wire 8 v" I0 [7:0] $end
$var wire 8 w" I1 [7:0] $end
$var wire 1 I sel $end
$var reg 8 x" O [7:0] $end
$upscope $end
$scope module addressMux $end
$var wire 8 y" I0 [7:0] $end
$var wire 8 z" I1 [7:0] $end
$var wire 8 {" I2 [7:0] $end
$var wire 8 |" I3 [7:0] $end
$var wire 2 }" sel [1:0] $end
$var reg 8 ~" out [7:0] $end
$upscope $end
$upscope $end
$upscope $end
$upscope $end
$enddefinitions $end
#0
$dumpvars
bx ~"
b0 }"
bx |"
bx {"
bx z"
bx y"
b0 x"
b0 w"
bx v"
bx u"
b0 t"
b0 s"
bx r"
bx q"
b0 p"
bx o"
bx n"
b0 m"
bx l"
bx k"
bx j"
bx i"
bx h"
bx g"
bx f"
bx e"
bx d"
bx c"
bx b"
bx a"
bx `"
bx _"
x^"
bz ]"
bx \"
x["
bz Z"
bx Y"
xX"
bz W"
bx V"
xU"
bz T"
xS"
xR"
xQ"
xP"
bx O"
xN"
xM"
bx L"
bx K"
bx J"
bx I"
bx H"
bx G"
bx F"
bz E"
bx D"
bx C"
bx B"
zA"
bx @"
x?"
bx >"
bx ="
bx <"
x;"
bx :"
bx 9"
bx 8"
x7"
x6"
bx 5"
bx 4"
bx 3"
bx 2"
bx 1"
bx 0"
bx /"
bx ."
bx -"
bx ,"
bx +"
bx *"
bx )"
bx ("
bx '"
bx &"
bx %"
b0 $"
b0 #"
bx ""
bx !"
0~
b0 }
bx |
b0 {
bx z
b0 y
bx x
0w
b0 v
zu
1t
xs
b0 r
bx q
xp
xo
xn
1m
b0 l
0k
b0 j
xi
1h
b0 g
b0 f
bx e
bx d
bx c
bx b
bx a
bx `
x_
x^
x]
x\
bx [
bx Z
b0 Y
b0 X
bx W
b0 V
bx U
b11000000 T
bx S
b11000000 R
b11000000 Q
bx P
bx O
xN
bx M
bx L
b0 K
0J
xI
xH
b0 G
xF
bx E
xD
bx C
0B
0A
bz @
bx ?
bx >
b11000000 =
0<
bx ;
bx :
b0 9
bx 8
07
b0 6
b0 5
04
03
02
01
00
0/
0.
b0 -
0,
b0 +
b0 *
bx )
b0 (
bx '
bx &
bz %
bx $
b11000000 #
bx "
bx !
$end
#50
0^"
0["
0X"
0U"
06"
0;"
0?"
0S"
0R"
0Q"
0P"
b0 J"
b0 %"
b11 !"
b0 z
b0 Z
b0 :
b0 ("
b0 e
b0 M
b0 L"
b0 j"
b0 [
b0 ?
b0 C"
b0 D"
b0 O"
b0 d"
b1 x"
b1 (
b1 G
b1 p"
b1 t"
b1100 a
b1100 x
b1100 |
b1100 ""
b0 d
b0 c
b0 b
b0 q
b11 `
0\
0n
0]
0o
1^
1p
1_
1i
b1 s"
b1 w"
0h
0D
xk
xB
xt
b0 ~"
b0 !
b0 8
b0 O
b0 l"
b11000000 S
b11000000 '
b11000000 E
b11000000 W
b0 u"
b0 q"
b0 y"
bx Q
bx #
bx =
bx R
bx T
b1 f
b1 X
b1 g
b1 j
b1 l
b1 r
b1 v
b1 y
b1 }
b1 #"
1,
1<
#100
0,
0<
#150
z7"
bz k"
bz )
bz L
bz '"
bz /"
bz 2"
bz 5"
bz K"
bz r"
bz {"
bz e"
bz $
bz >
bz &"
bz ."
bz 1"
bz 4"
bz B"
bz n"
bz |"
bz V"
bz F"
bz `"
bz f"
bx x"
bx (
bx G
bx p"
bx t"
xU"
xP"
b0x J"
b10 s"
b10 w"
1~
xA
0m
0I
0k
0B
0t
0H
b1 ~"
b1 !
b1 8
b1 O
b1 l"
b1 u"
b1 q"
b1 y"
b10 f
b10 X
b10 g
b10 j
b10 l
b10 r
b10 v
b10 y
b10 }
b10 #"
b11000000 Q
b11000000 #
b11000000 =
b11000000 R
b11000000 T
1,
1<
#200
0,
0<
#250
b11 z
b1 [
b0x ?
b0x C"
b0x D"
b0x O"
b0x d"
b0 a
b0 x
b0 |
b0 ""
b1 c
b0 `
0^
0p
0_
0i
bx s"
bx w"
bx ~"
bx !
bx 8
bx O
bx l"
b100 S
b100 '
b100 E
b100 W
bx u"
bx q"
bx y"
bx x"
bx (
bx G
bx p"
bx t"
0U"
0P"
b0 J"
0~
0A
1h
xD
1m
xI
1t
xH
b100 Q
b100 #
b100 =
b100 R
b100 T
b0 f
b0 X
b0 g
b0 j
b0 l
b0 r
b0 v
b0 y
b0 }
b0 #"
1,
1<
#300
0,
0<
#350
0h
0D
0t
0H
b1 f
b1 X
b1 g
b1 j
b1 l
b1 r
b1 v
b1 y
b1 }
b1 #"
bx Q
bx #
bx =
bx R
bx T
1,
1<
#400
0,
0<
#450
1~
xA
b11 {
bx K
bx Y
0m
0I
b10 f
b10 X
b10 g
b10 j
b10 l
b10 r
b10 v
b10 y
b10 }
b10 #"
1,
1<
#500
0,
0<
#550
x6"
x;"
x?"
b0 !"
b0 z
bx Z
bx :
bx ("
bx e
bx M
bx L"
bx j"
bx [
bx ?
bx C"
bx D"
bx O"
bx d"
bx a
bx x
bx |
bx ""
bx d
bx c
bx b
bx q
bx `
x\
xn
x]
xo
x^
xp
x_
xi
bx S
bx '
bx E
bx W
0~
0A
b0 {
b0 K
b0 Y
1m
xI
1h
xD
1t
xH
b0 f
b0 X
b0 g
b0 j
b0 l
b0 r
b0 v
b0 y
b0 }
b0 #"
1,
1<
#600
0,
0<
#650
0h
0D
xk
xB
xt
b1 f
b1 X
b1 g
b1 j
b1 l
b1 r
b1 v
b1 y
b1 }
b1 #"
1,
1<
#700
0,
0<
#750
xw
xJ
0m
0I
0k
0B
b10 f
b10 X
b10 g
b10 j
b10 l
b10 r
b10 v
b10 y
b10 }
b10 #"
1,
1<
#800
0,
0<
#850
1h
xD
1m
xI
0w
0J
1t
b0 f
b0 X
b0 g
b0 j
b0 l
b0 r
b0 v
b0 y
b0 }
b0 #"
1,
1<
#900
0,
0<
#950
xk
xB
0h
0D
xt
b1 f
b1 X
b1 g
b1 j
b1 l
b1 r
b1 v
b1 y
b1 }
b1 #"
1,
1<
